README.md
setup.py
bin/pulr
pulr/__init__.py
pulr/beacons.py
pulr/dp.py
pulr/outputs.py
pulr.egg-info/PKG-INFO
pulr.egg-info/SOURCES.txt
pulr.egg-info/dependency_links.txt
pulr.egg-info/requires.txt
pulr.egg-info/top_level.txt
pulr/proto/__init__.py
pulr/proto/enip.py
pulr/proto/modbus.py
pulr/proto/snmp.py